{"note":"This file is an internal implementation detail to speed up HTML report generation. Its format can change at any time. You might be looking for the JSON report: https://coverage.rtfd.io/cmd.html#cmd-json","format":5,"version":"7.10.6","globals":"0fa625b1eb609ca77c61634c9a6c1019","files":{"z_e4d0983e0b10c261___init___py":{"hash":"e6baa73cda2916dad605215f937a92e1","index":{"url":"z_e4d0983e0b10c261___init___py.html","file":"task1\\__init__.py","description":"","nums":{"precision":0,"n_files":1,"n_statements":0,"n_excluded":0,"n_missing":0,"n_branches":0,"n_partial_branches":0,"n_missing_branches":0}}},"z_4fe9fbc85f41931f_main_py":{"hash":"ffa8cc79f3a808f34d50df4725d53f55","index":{"url":"z_4fe9fbc85f41931f_main_py.html","file":"task1\\api\\main.py","description":"","nums":{"precision":0,"n_files":1,"n_statements":67,"n_excluded":0,"n_missing":21,"n_branches":0,"n_partial_branches":0,"n_missing_branches":0}}},"z_4fe9fbc85f41931f_schemas_py":{"hash":"4d352cd1922eb3dfe664be99215d23ae","index":{"url":"z_4fe9fbc85f41931f_schemas_py.html","file":"task1\\api\\schemas.py","description":"","nums":{"precision":0,"n_files":1,"n_statements":43,"n_excluded":0,"n_missing":0,"n_branches":0,"n_partial_branches":0,"n_missing_branches":0}}},"z_4fe9fbc85f41931f_utils_py":{"hash":"2dceb71dcf697b3be748e56dc511ec7a","index":{"url":"z_4fe9fbc85f41931f_utils_py.html","file":"task1\\api\\utils.py","description":"","nums":{"precision":0,"n_files":1,"n_statements":2,"n_excluded":0,"n_missing":0,"n_branches":0,"n_partial_branches":0,"n_missing_branches":0}}},"z_8ba89f46916b1a2e___init___py":{"hash":"e6baa73cda2916dad605215f937a92e1","index":{"url":"z_8ba89f46916b1a2e___init___py.html","file":"task1\\data\\__init__.py","description":"","nums":{"precision":0,"n_files":1,"n_statements":0,"n_excluded":0,"n_missing":0,"n_branches":0,"n_partial_branches":0,"n_missing_branches":0}}},"z_8ba89f46916b1a2e_dataloader_py":{"hash":"714cee162e45a06d7116b91295ca5044","index":{"url":"z_8ba89f46916b1a2e_dataloader_py.html","file":"task1\\data\\dataloader.py","description":"","nums":{"precision":0,"n_files":1,"n_statements":14,"n_excluded":0,"n_missing":0,"n_branches":0,"n_partial_branches":0,"n_missing_branches":0}}},"z_8ba89f46916b1a2e_preprocessing_py":{"hash":"fbc5da336da9f191a5a22f683ae271bc","index":{"url":"z_8ba89f46916b1a2e_preprocessing_py.html","file":"task1\\data\\preprocessing.py","description":"","nums":{"precision":0,"n_files":1,"n_statements":148,"n_excluded":0,"n_missing":27,"n_branches":0,"n_partial_branches":0,"n_missing_branches":0}}},"z_8ba89f46916b1a2e_utils_py":{"hash":"953dae4d98fbd0ce2d52867c960f51db","index":{"url":"z_8ba89f46916b1a2e_utils_py.html","file":"task1\\data\\utils.py","description":"","nums":{"precision":0,"n_files":1,"n_statements":19,"n_excluded":0,"n_missing":0,"n_branches":0,"n_partial_branches":0,"n_missing_branches":0}}},"z_08b2ada9efa0de1a___init___py":{"hash":"e6baa73cda2916dad605215f937a92e1","index":{"url":"z_08b2ada9efa0de1a___init___py.html","file":"task1\\training\\__init__.py","description":"","nums":{"precision":0,"n_files":1,"n_statements":0,"n_excluded":0,"n_missing":0,"n_branches":0,"n_partial_branches":0,"n_missing_branches":0}}},"z_08b2ada9efa0de1a_main_py":{"hash":"cfb8124059b1661e7926ea666f64d29c","index":{"url":"z_08b2ada9efa0de1a_main_py.html","file":"task1\\training\\main.py","description":"","nums":{"precision":0,"n_files":1,"n_statements":36,"n_excluded":0,"n_missing":36,"n_branches":0,"n_partial_branches":0,"n_missing_branches":0}}},"z_08b2ada9efa0de1a_models_py":{"hash":"e105915e200756d606f5540c67f9c71e","index":{"url":"z_08b2ada9efa0de1a_models_py.html","file":"task1\\training\\models.py","description":"","nums":{"precision":0,"n_files":1,"n_statements":15,"n_excluded":0,"n_missing":0,"n_branches":0,"n_partial_branches":0,"n_missing_branches":0}}},"z_08b2ada9efa0de1a_training_py":{"hash":"51b1b40e68bb2eb650957fc5c580d6b0","index":{"url":"z_08b2ada9efa0de1a_training_py.html","file":"task1\\training\\training.py","description":"","nums":{"precision":0,"n_files":1,"n_statements":57,"n_excluded":0,"n_missing":13,"n_branches":0,"n_partial_branches":0,"n_missing_branches":0}}},"z_f6557a55164303c4___init___py":{"hash":"e6baa73cda2916dad605215f937a92e1","index":{"url":"z_f6557a55164303c4___init___py.html","file":"task2\\__init__.py","description":"","nums":{"precision":0,"n_files":1,"n_statements":0,"n_excluded":0,"n_missing":0,"n_branches":0,"n_partial_branches":0,"n_missing_branches":0}}},"z_9ad7226ca899664a_test_dataloader_py":{"hash":"51cbcbed4dc1cf2b3ab36e9328a4fcda","index":{"url":"z_9ad7226ca899664a_test_dataloader_py.html","file":"task2\\tests\\test_dataloader.py","description":"","nums":{"precision":0,"n_files":1,"n_statements":6,"n_excluded":0,"n_missing":0,"n_branches":0,"n_partial_branches":0,"n_missing_branches":0}}},"z_9ad7226ca899664a_test_integration_py":{"hash":"9fda9ad456b72d65019531d59311eec6","index":{"url":"z_9ad7226ca899664a_test_integration_py.html","file":"task2\\tests\\test_integration.py","description":"","nums":{"precision":0,"n_files":1,"n_statements":50,"n_excluded":0,"n_missing":0,"n_branches":0,"n_partial_branches":0,"n_missing_branches":0}}},"z_9ad7226ca899664a_test_preprocessing_py":{"hash":"a911b02735a8f2e0bcfa3a3d6d4d52e2","index":{"url":"z_9ad7226ca899664a_test_preprocessing_py.html","file":"task2\\tests\\test_preprocessing.py","description":"","nums":{"precision":0,"n_files":1,"n_statements":28,"n_excluded":0,"n_missing":0,"n_branches":0,"n_partial_branches":0,"n_missing_branches":0}}},"z_9ad7226ca899664a_test_training_py":{"hash":"f501860547ee21b644e843233530efb9","index":{"url":"z_9ad7226ca899664a_test_training_py.html","file":"task2\\tests\\test_training.py","description":"","nums":{"precision":0,"n_files":1,"n_statements":26,"n_excluded":0,"n_missing":0,"n_branches":0,"n_partial_branches":0,"n_missing_branches":0}}}}}